mcp_proxy_adapter/__init__.py
mcp_proxy_adapter/__main__.py
mcp_proxy_adapter/config.py
mcp_proxy_adapter/custom_openapi.py
mcp_proxy_adapter/main.py
mcp_proxy_adapter/openapi.py
mcp_proxy_adapter/version.py
mcp_proxy_adapter/api/__init__.py
mcp_proxy_adapter/api/app.py
mcp_proxy_adapter/api/handlers.py
mcp_proxy_adapter/api/schemas.py
mcp_proxy_adapter/api/tool_integration.py
mcp_proxy_adapter/api/tools.py
mcp_proxy_adapter/api/core/__init__.py
mcp_proxy_adapter/api/core/app_factory.py
mcp_proxy_adapter/api/core/app_factory_certificates.py
mcp_proxy_adapter/api/core/app_factory_config.py
mcp_proxy_adapter/api/core/app_factory_routes.py
mcp_proxy_adapter/api/core/app_factory_validators.py
mcp_proxy_adapter/api/core/lifespan_manager.py
mcp_proxy_adapter/api/core/registration_context.py
mcp_proxy_adapter/api/core/registration_manager.py
mcp_proxy_adapter/api/core/registration_tasks.py
mcp_proxy_adapter/api/core/ssl_context_factory.py
mcp_proxy_adapter/api/core/registration/__init__.py
mcp_proxy_adapter/api/core/registration/config_parsers.py
mcp_proxy_adapter/api/core/registration/context_builder.py
mcp_proxy_adapter/api/core/registration/helpers.py
mcp_proxy_adapter/api/core/registration/metadata_builders.py
mcp_proxy_adapter/api/core/registration/models.py
mcp_proxy_adapter/api/core/registration/resolvers.py
mcp_proxy_adapter/api/core/registration/url_builders.py
mcp_proxy_adapter/api/core/registration_manager/__init__.py
mcp_proxy_adapter/api/core/registration_manager/helpers.py
mcp_proxy_adapter/api/core/registration_manager/manager.py
mcp_proxy_adapter/api/core/registration_manager/status.py
mcp_proxy_adapter/api/middleware/__init__.py
mcp_proxy_adapter/api/middleware/base.py
mcp_proxy_adapter/api/middleware/command_permission_middleware.py
mcp_proxy_adapter/api/middleware/error_handling.py
mcp_proxy_adapter/api/middleware/factory.py
mcp_proxy_adapter/api/middleware/logging.py
mcp_proxy_adapter/api/middleware/performance.py
mcp_proxy_adapter-6.9.106.dist-info/METADATA
mcp_proxy_adapter-6.9.106.dist-info/WHEEL
mcp_proxy_adapter-6.9.106.dist-info/entry_points.txt
mcp_proxy_adapter-6.9.106.dist-info/top_level.txt
mcp_proxy_adapter-6.9.106.dist-info/RECORD
