Metadata-Version: 2.4
Name: mcp-proxy-adapter
Version: 6.9.106
Summary: Powerful JSON-RPC microservices framework with built-in security, authentication, proxy registration, queue-backed command execution for long-running operations, and configurable HTTP timeouts for mTLS connections
Home-page: https://github.com/maverikod/mcp-proxy-adapter
Author: Vasiliy Zdanovskiy
Author-email: Vasiliy Zdanovskiy <vasilyvz@gmail.com>
Maintainer: Vasiliy Zdanovskiy
Maintainer-email: Vasiliy Zdanovskiy <vasilyvz@gmail.com>
License: MIT
Project-URL: Homepage, https://github.com/maverikod/mcp-proxy-adapter
Project-URL: Documentation, https://github.com/maverikod/mcp-proxy-adapter#readme
Project-URL: Source, https://github.com/maverikod/mcp-proxy-adapter
Project-URL: Tracker, https://github.com/maverikod/mcp-proxy-adapter/issues
Project-URL: PyPI, https://pypi.org/project/mcp-proxy-adapter/
Keywords: json-rpc,microservices,fastapi,security,authentication,authorization,proxy,mcp,mtls,ssl,rest,api
Classifier: Development Status :: 4 - Beta
Classifier: Intended Audience :: Developers
Classifier: Operating System :: OS Independent
Classifier: Programming Language :: Python :: 3
Classifier: Programming Language :: Python :: 3.9
Classifier: Programming Language :: Python :: 3.10
Classifier: Programming Language :: Python :: 3.11
Classifier: Programming Language :: Python :: 3.12
Classifier: Framework :: FastAPI
Classifier: Topic :: Internet :: WWW/HTTP :: HTTP Servers
Classifier: Topic :: Security
Classifier: Topic :: Software Development :: Libraries :: Python Modules
Requires-Python: >=3.9
Requires-Dist: fastapi<1.0.0,>=0.95.0
Requires-Dist: pydantic>=2.0.0
Requires-Dist: hypercorn<1.0.0,>=0.15.0
Requires-Dist: docstring-parser<1.0.0,>=0.15
Requires-Dist: typing-extensions<5.0.0,>=4.5.0
Requires-Dist: jsonrpc>=1.2.0
Requires-Dist: psutil>=5.9.0
Requires-Dist: mcp_security_framework>=1.5.1
Requires-Dist: flask>=3.1.0
Requires-Dist: packaging>=20.0
Requires-Dist: aiohttp<4.0.0,>=3.8.0
Requires-Dist: httpx>=0.24.0
Requires-Dist: queuemgr>=1.0.13
Requires-Dist: requests>=2.31.0
Provides-Extra: dev
Requires-Dist: pytest>=7.0.0; extra == "dev"
Requires-Dist: pytest-asyncio>=0.20.0; extra == "dev"
Requires-Dist: pytest-cov>=4.0.0; extra == "dev"
Requires-Dist: black>=23.0.0; extra == "dev"
Requires-Dist: isort>=5.12.0; extra == "dev"
Provides-Extra: test
Requires-Dist: pytest>=7.0.0; extra == "test"
Requires-Dist: pytest-asyncio>=0.21.0; extra == "test"
Requires-Dist: pytest-cov>=4.0.0; extra == "test"
Requires-Dist: httpx>=0.24.0; extra == "test"
Requires-Dist: pytest-mock>=3.10.0; extra == "test"
Provides-Extra: examples
Dynamic: author
Dynamic: home-page
Dynamic: maintainer
Dynamic: requires-python
